<?xml version="1.0" encoding="ISO-8859-1"?>
<!--
To change this license header, choose License Headers in Project Properties.
To change this template file, choose Tools | Templates
and open the template in the editor.
-->
<CatalogoProveedores>
    <tablaProgramaDesarrollo>
		<query>
			select * from programa_desarrollo_modulo;
		</query>
	</tablaProgramaDesarrollo>
    <guardarProgramaDesarrolloModulo>
		<query>
			INSERT INTO programa_desarrollo_modulo (cve_prog_des, cve_modulo, nombre_modulo, num_materias, color, usuario_registro)
VALUES (?, 1, ?, ?, ?,1);

		</query>
	</guardarProgramaDesarrolloModulo>
    <selectProgramaDesarollo>
		<query>
			select * from programa_desarrollo;
		</query>
	</selectProgramaDesarollo>
	<desactivarProgramaDesarrolloModulos>
		<query>
			UPDATE programa_desarrollo_modulo
			SET activo = 0
			WHERE cve_prog_des = ? AND nombre_modulo = ?;

		</query>
	</desactivarProgramaDesarrolloModulos>
</CatalogoProveedores>